schema_enforcer/__init__.py
schema_enforcer/ansible_inventory.py
schema_enforcer/cli.py
schema_enforcer/config.py
schema_enforcer/exceptions.py
schema_enforcer/instances/file.py
schema_enforcer/schemas/draft7_schema.json
schema_enforcer/schemas/jsonschema.py
schema_enforcer/schemas/manager.py
schema_enforcer/schemas/validator.py
schema_enforcer/utils.py
schema_enforcer/validation.py
schema_enforcer-1.5.1.dist-info/METADATA
schema_enforcer-1.5.1.dist-info/WHEEL
schema_enforcer-1.5.1.dist-info/entry_points.txt
schema_enforcer-1.5.1.dist-info/licenses/LICENSE
schema_enforcer-1.5.1.dist-info/RECORD
