Metadata-Version: 2.4
Name: schema-enforcer
Version: 1.5.1
Summary: Tool/Framework for testing structured data against schema definitions
License: Apache-2.0
License-File: LICENSE
Author: Network to Code, LLC
Author-email: info@networktocode.com
Requires-Python: >=3.10,<3.14
Classifier: Development Status :: 5 - Production/Stable
Classifier: Intended Audience :: Developers
Classifier: License :: OSI Approved :: Apache Software License
Classifier: Programming Language :: Python :: 3
Classifier: Programming Language :: Python :: 3.10
Classifier: Programming Language :: Python :: 3.11
Classifier: Programming Language :: Python :: 3.12
Classifier: Programming Language :: Python :: 3.13
Provides-Extra: ansible
Provides-Extra: ansible-core
Requires-Dist: ansible (>=9.0.0) ; extra == "ansible"
Requires-Dist: ansible-core (>=2.16.0) ; extra == "ansible-core"
Requires-Dist: click (>=8.2.0)
Requires-Dist: jinja2 (>=3.1.6,<4.0.0)
Requires-Dist: jmespath (>=1.0.1,<2.0.0)
Requires-Dist: jsonpointer (>=2.1.0,<3.0.0)
Requires-Dist: jsonref (>=1.1.0,<2.0.0)
Requires-Dist: jsonschema[format-nongpl] (>=4.6,<5.0)
Requires-Dist: pydantic (>=2.0.0,<3.0.0)
Requires-Dist: pydantic-settings (>=2.1,<3.0)
Requires-Dist: rich (>=9.5)
Requires-Dist: ruamel.yaml (>=0.18,<0.19)
Requires-Dist: termcolor (>=3.2.0)
Requires-Dist: tomli ; python_version < "3.11"
Project-URL: Homepage, https://github.com/networktocode/schema-enforcer
Project-URL: Repository, https://github.com/networktocode/schema-enforcer
